metrology/__init__.py
metrology/exceptions.py
metrology/registry.py
metrology/wsgi.py
metrology/instruments/__init__.py
metrology/instruments/counter.py
metrology/instruments/derive.py
metrology/instruments/gauge.py
metrology/instruments/healthcheck.py
metrology/instruments/histogram.py
metrology/instruments/meter.py
metrology/instruments/timer.py
metrology/reporter/__init__.py
metrology/reporter/base.py
metrology/reporter/ganglia.py
metrology/reporter/graphite.py
metrology/reporter/librato.py
metrology/reporter/logger.py
metrology/reporter/statsd.py
metrology/stats/__init__.py
metrology/stats/ewma.py
metrology/stats/sample.py
metrology/stats/snapshot.py
metrology/utils/__init__.py
metrology/utils/periodic.py
metrology-1.3.0.dist-info/AUTHORS
metrology-1.3.0.dist-info/LICENSE
metrology-1.3.0.dist-info/METADATA
metrology-1.3.0.dist-info/WHEEL
metrology-1.3.0.dist-info/pbr.json
metrology-1.3.0.dist-info/top_level.txt
metrology-1.3.0.dist-info/RECORD
