Metadata-Version: 2.1
Name: metrology
Version: 1.3.0
Summary: A library to easily measure what\'s going on in your python.
Home-page: https://github.com/cyberdelia/metrology
Author: Timothée Peignier'
Author-email: timothee.peignier@tryphon.org
License: MIT License
Platform: UNKNOWN
Classifier: Intended Audience :: Developers
Classifier: License :: OSI Approved :: MIT License
Classifier: Operating System :: OS Independent
Classifier: Programming Language :: Python
Classifier: Programming Language :: Python :: 3
Classifier: Topic :: Utilities
Requires-Dist: astrolabe (>=0.4.0)
Requires-Dist: atomic (>=0.7.0)
Requires-Dist: ganglia
Requires-Dist: requests
